Workbook

Sheet Database
A1: Ingredient | B1: Energy (kcal) | C1: Protein (g) | D1: Carbohydrate (g) | E1: Total sugars (g) | F1: Total fat (g) | G1: Saturated fat (g) | H1: Trans fat (g) | I1: Cholesterol (mg) | J1: Sodium (mg) | K1: Added-sugar ingredient? (1/0) | L1: Source / note
A2: Prawns, fresh, cleaned | B2: 77 | C2: 15.3 | D2: 0.5 | E2: 0 | F2: 1.3 | G2: 0.3 | H2: 0 | I2: 150 | J2: 250 | K2: 0 | L2: IFCT 2017 / USDA, shrimp raw
A3: Dates, dried | B3: 320 | C3: 2.5 | D3: 75 | E3: 65 | F3: 0.4 | G3: 0.1 | H3: 0 | I3: 0 | J3: 5 | K3: 0 | L3: IFCT 2017, dates dry (sugar intrinsic, not 'added')
A4: Gingelly (sesame) oil | B4: 899 | C4: 0 | D4: 0 | E4: 0 | F4: 99.85 | G4: 14.18 | H4: 0 | I4: 0 | J4: 0 | K4: 0 | L4: From supplier label: RG Foods Gingelly Oil Grade II (MUFA 39.74 g, PUFA 41.71 g)
A5: Mustard oil | B5: 900 | C5: 0 | D5: 0 | E5: 0 | F5: 100 | G5: 12 | H5: 0 | I5: 0 | J5: 0 | K5: 0
A6: Coconut oil | B6: 900 | C6: 0 | D6: 0 | E6: 0 | F6: 100 | G6: 87 | H6: 0 | I6: 0 | J6: 0 | K6: 0
A7: Sunflower / refined oil | B7: 900 | C7: 0 | D7: 0 | E7: 0 | F7: 100 | G7: 11 | H7: 0 | I7: 0 | J7: 0 | K7: 0
A8: Vinegar, synthetic 4% | B8: 0 | C8: 0 | D8: 0 | E8: 0 | F8: 0 | G8: 0 | H8: 0 | I8: 0 | J8: 0 | K8: 0 | L8: Negligible nutrients; mostly evaporates
A9: Garlic, fresh | B9: 140 | C9: 6.3 | D9: 28 | E9: 1.5 | F9: 0.3 | G9: 0.1 | H9: 0 | I9: 0 | J9: 15 | K9: 0 | L9: IFCT 2017
A10: Green chilli, fresh | B10: 30 | C10: 2 | D10: 4.5 | E10: 2 | F10: 0.5 | G10: 0.1 | H10: 0 | I10: 0 | J10: 5 | K10: 0 | L10: IFCT 2017
A11: Ginger, fresh | B11: 55 | C11: 2 | D11: 10 | E11: 1.5 | F11: 0.8 | G11: 0.2 | H11: 0 | I11: 0 | J11: 15 | K11: 0 | L11: IFCT 2017
A12: Curry leaves, fresh | B12: 100 | C12: 6 | D12: 18 | E12: 2 | F12: 1 | G12: 0.2 | H12: 0 | I12: 0 | J12: 20 | K12: 0 | L12: IFCT 2017
A13: Onion, fresh | B13: 40 | C13: 1.2 | D13: 9 | E13: 4 | F13: 0.1 | G13: 0 | H13: 0 | I13: 0 | J13: 4 | K13: 0 | L13: IFCT 2017
A14: Red chilli powder | B14: 290 | C14: 12 | D14: 35 | E14: 8 | F14: 12 | G14: 2 | H14: 0 | I14: 0 | J14: 30 | K14: 0 | L14: IFCT 2017, chilli red dry
A15: Kashmiri chilli powder | B15: 290 | C15: 12 | D15: 35 | E15: 8 | F15: 12 | G15: 2 | H15: 0 | I15: 0 | J15: 30 | K15: 0 | L15: Same as red chilli powder
A16: Turmeric powder | B16: 320 | C16: 8 | D16: 65 | E16: 3 | F16: 4 | G16: 2 | H16: 0 | I16: 0 | J16: 30 | K16: 0 | L16: IFCT 2017
A17: Mustard seed / powder | B17: 520 | C17: 22 | D17: 25 | E17: 5 | F17: 38 | G17: 2 | H17: 0 | I17: 0 | J17: 10 | K17: 0 | L17: IFCT 2017
A18: Fenugreek seed / powder | B18: 330 | C18: 26 | D18: 44 | E18: 1 | F18: 6 | G18: 1.5 | H18: 0 | I18: 0 | J18: 60 | K18: 0 | L18: IFCT 2017
A19: Dry ginger powder | B19: 340 | C19: 9 | D19: 70 | E19: 3 | F19: 4 | G19: 2 | H19: 0 | I19: 0 | J19: 30 | K19: 0 | L19: USDA
... A30: Tamarind pulp | B30: 240 | C30: 3 | D30: 62 | E30: 40 | F30: 0.5 | G30: 0.2 | H30: 0 | I30: 0 | J30: 30 | K30: 0 | L30: IFCT 2017
A31: Water | B31: 0 | C31: 0 | D31: 0 | E31: 0 | F31: 0 | G31: 0 | H31: 0 | I31: 0 | J31: 0 | K31: 0
A33: How to use this sheet
A34: All values are per 100 g of the ingredient as it goes into the pot (raw). Blue cells are editable.
A35: Values are approximate, drawn from IFCT 2017 (NIN Hyderabad, Indian Food Composition Tables) and USDA FoodData Central. Verify any ingredient that dominates your recipe (oil, salt, meat, dates) against the IFCT table before printing.
A36: To add an ingredient: type it on a new row below the last one, fill the numbers, then extend the dropdown range on the Recipe sheet (Data > Validation) if needed. The dropdown already covers rows 2 to 60.
A37: Added-sugar flag: 1 only for sugar, jaggery, honey, syrups. Sugar naturally in dates, mango, etc. is NOT 'added sugar' under FSSAI.
A38: Sodium from salt: 1 g salt = 393 mg sodium. This single number drives most of your sodium figure, so weigh salt accurately.

Sheet Recipe
A1: Lailark Kitchen: Nutrition Calculator (per 100 g, FSSAI panel)
A2: Yellow cells: you fill in. Everything else calculates. One recipe per copy of this sheet (right-click tab > Move or Copy).
A4: Product name | B4: Prawns & Dates Pickle
A5: Finished batch weight, weighed after cooking and settling (g) | B5: 4600
A6: Serving size for the optional 'per serve' column (g) | B6: 15
A7: Batch number / date (for your records) | B7: Batch 009, 04/09/2026
C8: 1 = all of it goes into the jars. Use e.g. 0.7 if 30% of the oil stays in the pan.
A9: Ingredient (pick from list) | B9: Weight in (g) | C9: Fraction ending up in jars | D9: Effective weight (g) | E9: Energy (kcal) | F9: Protein (g) | G9: Carb (g) | H9: Total sugars (g) | I9: Added sugars (g) | J9: Total fat (g) | K9: Sat fat (g) | L9: Trans fat (g) | M9: Cholesterol (mg) | N9: Sodium (mg)
A10: Prawns, fresh, cleaned | B10: 2700 | C10: 1 | D10: =IF(A10="",0,B10*C10) | E10: =IFERROR(D10*INDEX(Database!$B$2:$B$60,MATCH($A10,Database!$A$2:$A$60,0))/100,0) | F10: =IFERROR(D10*INDEX(Database!$C$2:$C$60,MATCH($A10,Database!$A$2:$A$60,0))/100,0) | G10: =IFERROR(D10*INDEX(Database!$D$2:$D$60,MATCH($A10,Database!$A$2:$A$60,0))/100,0) | H10: =IFERROR(D10*INDEX(Database!$E$2:$E$60,MATCH($A10,Database!$A$2:$A$60,0))/100,0) | I10: =IFERROR(H10*INDEX(Database!$K$2:$K$60,MATCH($A10,Database!$A$2:$A$60,0)),0) | J10: =IFERROR(D10*INDEX(Database!$F$2:$F$60,MATCH($A10,Database!$A$2:$A$60,0))/100,0) | K10: =IFERROR(D10*INDEX(Database!$G$2:$G$60,MATCH($A10,Database!$A$2:$A$60,0))/100,0) | L10: =IFERROR(D10*INDEX(Database!$H$2:$H$60,MATCH($A10,Database!$A$2:$A$60,0))/100,0) | M10: =IFERROR(D10*INDEX(Database!$I$2:$I$60,MATCH($A10,Database!$A$2:$A$60,0))/100,0) | N10: =IFERROR(D10*INDEX(Database!$J$2:$J$60,MATCH($A10,Database!$A$2:$A$60,0))/100,0)
A11: Dates, dried | B11: 1000 | C11: 1 | D11: =IF(A11="",0,B11*C11) | E11: =IFERROR(D11*INDEX(Database!$B$2:$B$60,MATCH($A11,Database!$A$2:$A$60,0))/100,0) | F11: =IFERROR(D11*INDEX(Database!$C$2:$C$60,MATCH($A11,Database!$A$2:$A$60,0))/100,0) | G11: =IFERROR(D11*INDEX(Database!$D$2:$D$60,MATCH($A11,Database!$A$2:$A$60,0))/100,0) | H11: =IFERROR(D11*INDEX(Database!$E$2:$E$60,MATCH($A11,Database!$A$2:$A$60,0))/100,0) | I11: =IFERROR(H11*INDEX(Database!$K$2:$K$60,MATCH($A11,Database!$A$2:$A$60,0)),0) | J11: =IFERROR(D11*INDEX(Database!$F$2:$F$60,MATCH($A11,Database!$A$2:$A$60,0))/100,0) | K11: =IFERROR(D11*INDEX(Database!$G$2:$G$60,MATCH($A11,Database!$A$2:$A$60,0))/100,0) | L11: =IFERROR(D11*INDEX(Database!$H$2:$H$60,MATCH($A11,Database!$A$2:$A$60,0))/100,0) | M11: =IFERROR(D11*INDEX(Database!$I$2:$I$60,MATCH($A11,Database!$A$2:$A$60,0))/100,0) | N11: =IFERROR(D11*INDEX(Database!$J$2:$J$60,MATCH($A11,Database!$A$2:$A$60,0))/100,0)
A12: Gingelly (sesame) oil | B12: 1420 | C12: 1 | D12: =IF(A12="",0,B12*C12) | E12: =IFERROR(D12*INDEX(Database!$B$2:$B$60,MATCH($A12,Database!$A$2:$A$60,0))/100,0) | F12: =IFERROR(D12*INDEX(Database!$C$2:$C$60,MATCH($A12,Database!$A$2:$A$60,0))/100,0) | G12: =IFERROR(D12*INDEX(Database!$D$2:$D$60,MATCH($A12,Database!$A$2:$A$60,0))/100,0) | H12: =IFERROR(D12*INDEX(Database!$E$2:$E$60,MATCH($A12,Database!$A$2:$A$60,0))/100,0) | I12: =IFERROR(H12*INDEX(Database!$K$2:$K$60,MATCH($A12,Database!$A$2:$A$60,0)),0) | J12: =IFERROR(D12*INDEX(Database!$F$2:$F$60,MATCH($A12,Database!$A$2:$A$60,0))/100,0) | K12: =IFERROR(D12*INDEX(Database!$G$2:$G$60,MATCH($A12,Database!$A$2:$A$60,0))/100,0) | L12: =IFERROR(D12*INDEX(Database!$H$2:$H$60,MATCH($A12,Database!$A$2:$A$60,0))/100,0) | M12: =IFERROR(D12*INDEX(Database!$I$2:$I$60,MATCH($A12,Database!$A$2:$A$60,0))/100,0) | N12: =IFERROR(D12*INDEX(Database!$J$2:$J$60,MATCH($A12,Database!$A$2:$A$60,0))/100,0)
A13: Vinegar, synthetic 4% | B13: 2000 | C13: 1 | D13: =IF(A13="",0,B13*C13) | E13: =IFERROR(D13*INDEX(Database!$B$2:$B$60,MATCH($A13,Database!$A$2:$A$60,0))/100,0) | F13: =IFERROR(D13*INDEX(Database!$C$2:$C$60,MATCH($A13,Database!$A$2:$A$60,0))/100,0) | G13: =IFERROR(D13*INDEX(Database!$D$2:$D$60,MATCH($A13,Database!$A$2:$A$60,0))/100,0) | H13: =IFERROR(D13*INDEX(Database!$E$2:$E$60,MATCH($A13,Database!$A$2:$A$60,0))/100,0) | I13: =IFERROR(H13*INDEX(Database!$K$2:$K$60,MATCH($A13,Database!$A$2:$A$60,0)),0) | J13: =IFERROR(D13*INDEX(Database!$F$2:$F$60,MATCH($A13,Database!$A$2:$A$60,0))/100,0) | K13: =IFERROR(D13*INDEX(Database!$G$2:$G$60,MATCH($A13,Database!$A$2:$A$60,0))/100,0) | L13: =IFERROR(D13*INDEX(Database!$H$2:$H$60,MATCH($A13,Database!$A$2:$A$60,0))/100,0) | M13: =IFERROR(D13*INDEX(Database!$I$2:$I$60,MATCH($A13,Database!$A$2:$A$60,0))/100,0) | N13: =IFERROR(D13*INDEX(Database!$J$2:$J$60,MATCH($A13,Database!$A$2:$A$60,0))/100,0)
A14: Garlic, fresh | B14: 390 | C14: 1 | D14: =IF(A14="",0,B14*C14) | E14: =IFERROR(D14*INDEX(Database!$B$2:$B$60,MATCH($A14,Database!$A$2:$A$60,0))/100,0) | F14: =IFERROR(D14*INDEX(Database!$C$2:$C$60,MATCH($A14,Database!$A$2:$A$60,0))/100,0) | G14: =IFERROR(D14*INDEX(Database!$D$2:$D$60,MATCH($A14,Database!$A$2:$A$60,0))/100,0) | H14: =IFERROR(D14*INDEX(Database!$E$2:$E$60,MATCH($A14,Database!$A$2:$A$60,0))/100,0) | I14: =IFERROR(H14*INDEX(Database!$K$2:$K$60,MATCH($A14,Database!$A$2:$A$60,0)),0) | J14: =IFERROR(D14*INDEX(Database!$F$2:$F$60,MATCH($A14,Database!$A$2:$A$60,0))/100,0) | K14: =IFERROR(D14*INDEX(Database!$G$2:$G$60,MATCH($A14,Database!$A$2:$A$60,0))/100,0) | L14: =IFERROR(D14*INDEX(Database!$H$2:$H$60,MATCH($A14,Database!$A$2:$A$60,0))/100,0) | M14: =IFERROR(D14*INDEX(Database!$I$2:$I$60,MATCH($A14,Database!$A$2:$A$60,0))/100,0) | N14: =IFERROR(D14*INDEX(Database!$J$2:$J$60,MATCH($A14,Database!$A$2:$A$60,0))/100,0)
A15: Green chilli, fresh | B15: 200 | C15: 1 | D15: =IF(A15="",0,B15*C15) | E15: =IFERROR(D15*INDEX(Database!$B$2:$B$60,MATCH($A15,Database!$A$2:$A$60,0))/100,0) | F15: =IFERROR(D15*INDEX(Database!$C$2:$C$60,MATCH($A15,Database!$A$2:$A$60,0))/100,0) | G15: =IFERROR(D15*INDEX(Database!$D$2:$D$60,MATCH($A15,Database!$A$2:$A$60,0))/100,0) | H15: =IFERROR(D15*INDEX(Database!$E$2:$E$60,MATCH($A15,Database!$A$2:$A$60,0))/100,0) | I15: =IFERROR(H15*INDEX(Database!$K$2:$K$60,MATCH($A15,Database!$A$2:$A$60,0)),0) | J15: =IFERROR(D15*INDEX(Database!$F$2:$F$60,MATCH($A15,Database!$A$2:$A$60,0))/100,0) | K15: =IFERROR(D15*INDEX(Database!$G$2:$G$60,MATCH($A15,Database!$A$2:$A$60,0))/100,0) | L15: =IFERROR(D15*INDEX(Database!$H$2:$H$60,MATCH($A15,Database!$A$2:$A$60,0))/100,0) | M15: =IFERROR(D15*INDEX(Database!$I$2:$I$60,MATCH($A15,Database!$A$2:$A$60,0))/100,0) | N15: =IFERROR(D15*INDEX(Database!$J$2:$J$60,MATCH($A15,Database!$A$2:$A$60,0))/100,0)
A16: Ginger, fresh | B16: 125 | C16: 1 | D16: =IF(A16="",0,B16*C16) | E16: =IFERROR(D16*INDEX(Database!$B$2:$B$60,MATCH($A16,Database!$A$2:$A$60,0))/100,0) | F16: =IFERROR(D16*INDEX(Database!$C$2:$C$60,MATCH($A16,Database!$A$2:$A$60,0))/100,0) | G16: =IFERROR(D16*INDEX(Database!$D$2:$D$60,MATCH($A16,Database!$A$2:$A$60,0))/100,0) | H16: =IFERROR(D16*INDEX(Database!$E$2:$E$60,MATCH($A16,Database!$A$2:$A$60,0))/100,0) | I16: =IFERROR(H16*INDEX(Database!$K$2:$K$60,MATCH($A16,Database!$A$2:$A$60,0)),0) | J16: =IFERROR(D16*INDEX(Database!$F$2:$F$60,MATCH($A16,Database!$A$2:$A$60,0))/100,0) | K16: =IFERROR(D16*INDEX(Database!$G$2:$G$60,MATCH($A16,Database!$A$2:$A$60,0))/100,0) | L16: =IFERROR(D16*INDEX(Database!$H$2:$H$60,MATCH($A16,Database!$A$2:$A$60,0))/100,0) | M16: =IFERROR(D16*INDEX(Database!$I$2:$I$60,MATCH($A16,Database!$A$2:$A$60,0))/100,0) | N16: =IFERROR(D16*INDEX(Database!$J$2:$J$60,MATCH($A16,Database!$A$2:$A$60,0))/100,0)
A17: Kashmiri chilli powder | B17: 60 | C17: 1 | D17: =IF(A17="",0,B17*C17) | E17: =IFERROR(D17*INDEX(Database!$B$2:$B$60,MATCH($A17,Database!$A$2:$A$60,0))/100,0) | F17: =IFERROR(D17*INDEX(Database!$C$2:$C$60,MATCH($A17,Database!$A$2:$A$60,0))/100,0) | G17: =IFERROR(D17*INDEX(Database!$D$2:$D$60,MATCH($A17,Database!$A$2:$A$60,0))/100,0) | H17: =IFERROR(D17*INDEX(Database!$E$2:$E$60,MATCH($A17,Database!$A$2:$A$60,0))/100,0) | I17: =IFERROR(H17*INDEX(Database!$K$2:$K$60,MATCH($A17,Database!$A$2:$A$60,0)),0) | J17: =IFERROR(D17*INDEX(Database!$F$2:$F$60,MATCH($A17,Database!$A$2:$A$60,0))/100,0) | K17: =IFERROR(D17*INDEX(Database!$G$2:$G$60,MATCH($A17,Database!$A$2:$A$60,0))/100,0) | L17: =IFERROR(D17*INDEX(Database!$H$2:$H$60,MATCH($A17,Database!$A$2:$A$60,0))/100,0) | M17: =IFERROR(D17*INDEX(Database!$I$2:$I$60,MATCH($A17,Database!$A$2:$A$60,0))/100,0) | N17: =IFERROR(D17*INDEX(Database!$J$2:$J$60,MATCH($A17,Database!$A$2:$A$60,0))/100,0)
A18: Red chilli powder | B18: 60 | C18: 1 | D18: =IF(A18="",0,B18*C18) | E18: =IFERROR(D18*INDEX(Database!$B$2:$B$60,MATCH($A18,Database!$A$2:$A$60,0))/100,0) | F18: =IFERROR(D18*INDEX(Database!$C$2:$C$60,MATCH($A18,Database!$A$2:$A$60,0))/100,0) | G18: =IFERROR(D18*INDEX(Database!$D$2:$D$60,MATCH($A18,Database!$A$2:$A$60,0))/100,0) | H18: =IFERROR(D18*INDEX(Database!$E$2:$E$60,MATCH($A18,Database!$A$2:$A$60,0))/100,0) | I18: =IFERROR(H18*INDEX(Database!$K$2:$K$60,MATCH($A18,Database!$A$2:$A$60,0)),0) | J18: =IFERROR(D18*INDEX(Database!$F$2:$F$60,MATCH($A18,Database!$A$2:$A$60,0))/100,0) | K18: =IFERROR(D18*INDEX(Database!$G$2:$G$60,MATCH($A18,Database!$A$2:$A$60,0))/100,0) | L18: =IFERROR(D18*INDEX(Database!$H$2:$H$60,MATCH($A18,Database!$A$2:$A$60,0))/100,0) | M18: =IFERROR(D18*INDEX(Database!$I$2:$I$60,MATCH($A18,Database!$A$2:$A$60,0))/100,0) | N18: =IFERROR(D18*INDEX(Database!$J$2:$J$60,MATCH($A18,Database!$A$2:$A$60,0))/100,0)
A19: Sugar, white | B19: 36 | C19: 1 | D19: =IF(A19="",0,B19*C19) | E19: =IFERROR(D19*INDEX(Database!$B$2:$B$60,MATCH($A19,Database!$A$2:$A$60,0))/100,0) | F19: =IFERROR(D19*INDEX(Database!$C$2:$C$60,MATCH($A19,Database!$A$2:$A$60,0))/100,0) | G19: =IFERROR(D19*INDEX(Database!$D$2:$D$60,MATCH($A19,Database!$A$2:$A$60,0))/100,0) | H19: =IFERROR(D19*INDEX(Database!$E$2:$E$60,MATCH($A19,Database!$A$2:$A$60,0))/100,0) | I19: =IFERROR(H19*INDEX(Database!$K$2:$K$60,MATCH($A19,Database!$A$2:$A$60,0)),0) | J19: =IFERROR(D19*INDEX(Database!$F$2:$F$60,MATCH($A19,Database!$A$2:$A$60,0))/100,0) | K19: =IFERROR(D19*INDEX(Database!$G$2:$G$60,MATCH($A19,Database!$A$2:$A$60,0))/100,0) | L19: =IFERROR(D19*INDEX(Database!$H$2:$H$60,MATCH($A19,Database!$A$2:$A$60,0))/100,0) | M19: =IFERROR(D19*INDEX(Database!$I$2:$I$60,MATCH($A19,Database!$A$2:$A$60,0))/100,0) | N19: =IFERROR(D19*INDEX(Database!$J$2:$J$60,MATCH($A19,Database!$A$2:$A$60,0))/100,0)
A20: Asafoetida, compounded | B20: 18 | C20: 1 | D20: =IF(A20="",0,B20*C20) | E20: =IFERROR(D20*INDEX(Database!$B$2:$B$60,MATCH($A20,Database!$A$2:$A$60,0))/100,0) | F20: =IFERROR(D20*INDEX(Database!$C$2:$C$60,MATCH($A20,Database!$A$2:$A$60,0))/100,0) | G20: =IFERROR(D20*INDEX(Database!$D$2:$D$60,MATCH($A20,Database!$A$2:$A$60,0))/100,0) | H20: =IFERROR(D20*INDEX(Database!$E$2:$E$60,MATCH($A20,Database!$A$2:$A$60,0))/100,0) | I20: =IFERROR(H20*INDEX(Database!$K$2:$K$60,MATCH($A20,Database!$A$2:$A$60,0)),0) | J20: =IFERROR(D20*INDEX(Database!$F$2:$F$60,MATCH($A20,Database!$A$2:$A$60,0))/100,0) | K20: =IFERROR(D20*INDEX(Database!$G$2:$G$60,MATCH($A20,Database!$A$2:$A$60,0))/100,0) | L20: =IFERROR(D20*INDEX(Database!$H$2:$H$60,MATCH($A20,Database!$A$2:$A$60,0))/100,0) | M20: =IFERROR(D20*INDEX(Database!$I$2:$I$60,MATCH($A20,Database!$A$2:$A$60,0))/100,0) | N20: =IFERROR(D20*INDEX(Database!$J$2:$J$60,MATCH($A20,Database!$A$2:$A$60,0))/100,0)
A21: Mustard seed / powder | B21: 16 | C21: 1 | D21: =IF(A21="",0,B21*C21) | E21: =IFERROR(D21*INDEX(Database!$B$2:$B$60,MATCH($A21,Database!$A$2:$A$60,0))/100,0) | F21: =IFERROR(D21*INDEX(Database!$C$2:$C$60,MATCH($A21,Database!$A$2:$A$60,0))/100,0) | G21: =IFERROR(D21*INDEX(Database!$D$2:$D$60,MATCH($A21,Database!$A$2:$A$60,0))/100,0) | H21: =IFERROR(D21*INDEX(Database!$E$2:$E$60,MATCH($A21,Database!$A$2:$A$60,0))/100,0) | I21: =IFERROR(H21*INDEX(Database!$K$2:$K$60,MATCH($A21,Database!$A$2:$A$60,0)),0) | J21: =IFERROR(D21*INDEX(Database!$F$2:$F$60,MATCH($A21,Database!$A$2:$A$60,0))/100,0) | K21: =IFERROR(D21*INDEX(Database!$G$2:$G$60,MATCH($A21,Database!$A$2:$A$60,0))/100,0) | L21: =IFERROR(D21*INDEX(Database!$H$2:$H$60,MATCH($A21,Database!$A$2:$A$60,0))/100,0) | M21: =IFERROR(D21*INDEX(Database!$I$2:$I$60,MATCH($A21,Database!$A$2:$A$60,0))/100,0) | N21: =IFERROR(D21*INDEX(Database!$J$2:$J$60,MATCH($A21,Database!$A$2:$A$60,0))/100,0)
... A26: Turmeric powder | B26: 7 | C26: 1 | D26: =IF(A26="",0,B26*C26) | E26: =IFERROR(D26*INDEX(Database!$B$2:$B$60,MATCH($A26,Database!$A$2:$A$60,0))/100,0) | F26: =IFERROR(D26*INDEX(Database!$C$2:$C$60,MATCH($A26,Database!$A$2:$A$60,0))/100,0) | G26: =IFERROR(D26*INDEX(Database!$D$2:$D$60,MATCH($A26,Database!$A$2:$A$60,0))/100,0) | H26: =IFERROR(D26*INDEX(Database!$E$2:$E$60,MATCH($A26,Database!$A$2:$A$60,0))/100,0) | I26: =IFERROR(H26*INDEX(Database!$K$2:$K$60,MATCH($A26,Database!$A$2:$A$60,0)),0) | J26: =IFERROR(D26*INDEX(Database!$F$2:$F$60,MATCH($A26,Database!$A$2:$A$60,0))/100,0) | K26: =IFERROR(D26*INDEX(Database!$G$2:$G$60,MATCH($A26,Database!$A$2:$A$60,0))/100,0) | L26: =IFERROR(D26*INDEX(Database!$H$2:$H$60,MATCH($A26,Database!$A$2:$A$60,0))/100,0) | M26: =IFERROR(D26*INDEX(Database!$I$2:$I$60,MATCH($A26,Database!$A$2:$A$60,0))/100,0) | N26: =IFERROR(D26*INDEX(Database!$J$2:$J$60,MATCH($A26,Database!$A$2:$A$60,0))/100,0)
C27: 1 | D27: =IF(A27="",0,B27*C27) | E27: =IFERROR(D27*INDEX(Database!$B$2:$B$60,MATCH($A27,Database!$A$2:$A$60,0))/100,0) | F27: =IFERROR(D27*INDEX(Database!$C$2:$C$60,MATCH($A27,Database!$A$2:$A$60,0))/100,0) | G27: =IFERROR(D27*INDEX(Database!$D$2:$D$60,MATCH($A27,Database!$A$2:$A$60,0))/100,0) | H27: =IFERROR(D27*INDEX(Database!$E$2:$E$60,MATCH($A27,Database!$A$2:$A$60,0))/100,0) | I27: =IFERROR(H27*INDEX(Database!$K$2:$K$60,MATCH($A27,Database!$A$2:$A$60,0)),0) | J27: =IFERROR(D27*INDEX(Database!$F$2:$F$60,MATCH($A27,Database!$A$2:$A$60,0))/100,0) | K27: =IFERROR(D27*INDEX(Database!$G$2:$G$60,MATCH($A27,Database!$A$2:$A$60,0))/100,0) | L27: =IFERROR(D27*INDEX(Database!$H$2:$H$60,MATCH($A27,Database!$A$2:$A$60,0))/100,0) | M27: =IFERROR(D27*INDEX(Database!$I$2:$I$60,MATCH($A27,Database!$A$2:$A$60,0))/100,0) | N27: =IFERROR(D27*INDEX(Database!$J$2:$J$60,MATCH($A27,Database!$A$2:$A$60,0))/100,0)
C28: 1 | D28: =IF(A28="",0,B28*C28) | E28: =IFERROR(D28*INDEX(Database!$B$2:$B$60,MATCH($A28,Database!$A$2:$A$60,0))/100,0) | F28: =IFERROR(D28*INDEX(Database!$C$2:$C$60,MATCH($A28,Database!$A$2:$A$60,0))/100,0) | G28: =IFERROR(D28*INDEX(Database!$D$2:$D$60,MATCH($A28,Database!$A$2:$A$60,0))/100,0) | H28: =IFERROR(D28*INDEX(Database!$E$2:$E$60,MATCH($A28,Database!$A$2:$A$60,0))/100,0) | I28: =IFERROR(H28*INDEX(Database!$K$2:$K$60,MATCH($A28,Database!$A$2:$A$60,0)),0) | J28: =IFERROR(D28*INDEX(Database!$F$2:$F$60,MATCH($A28,Database!$A$2:$A$60,0))/100,0) | K28: =IFERROR(D28*INDEX(Database!$G$2:$G$60,MATCH($A28,Database!$A$2:$A$60,0))/100,0) | L28: =IFERROR(D28*INDEX(Database!$H$2:$H$60,MATCH($A28,Database!$A$2:$A$60,0))/100,0) | M28: =IFERROR(D28*INDEX(Database!$I$2:$I$60,MATCH($A28,Database!$A$2:$A$60,0))/100,0) | N28: =IFERROR(D28*INDEX(Database!$J$2:$J$60,MATCH($A28,Database!$A$2:$A$60,0))/100,0)
C29: 1 | D29: =IF(A29="",0,B29*C29) | E29: =IFERROR(D29*INDEX(Database!$B$2:$B$60,MATCH($A29,Database!$A$2:$A$60,0))/100,0) | F29: =IFERROR(D29*INDEX(Database!$C$2:$C$60,MATCH($A29,Database!$A$2:$A$60,0))/100,0) | G29: =IFERROR(D29*INDEX(Database!$D$2:$D$60,MATCH($A29,Database!$A$2:$A$60,0))/100,0) | H29: =IFERROR(D29*INDEX(Database!$E$2:$E$60,MATCH($A29,Database!$A$2:$A$60,0))/100,0) | I29: =IFERROR(H29*INDEX(Database!$K$2:$K$60,MATCH($A29,Database!$A$2:$A$60,0)),0) | J29: =IFERROR(D29*INDEX(Database!$F$2:$F$60,MATCH($A29,Database!$A$2:$A$60,0))/100,0) | K29: =IFERROR(D29*INDEX(Database!$G$2:$G$60,MATCH($A29,Database!$A$2:$A$60,0))/100,0) | L29: =IFERROR(D29*INDEX(Database!$H$2:$H$60,MATCH($A29,Database!$A$2:$A$60,0))/100,0) | M29: =IFERROR(D29*INDEX(Database!$I$2:$I$60,MATCH($A29,Database!$A$2:$A$60,0))/100,0) | N29: =IFERROR(D29*INDEX(Database!$J$2:$J$60,MATCH($A29,Database!$A$2:$A$60,0))/100,0)
C30: 1 | D30: =IF(A30="",0,B30*C30) | E30: =IFERROR(D30*INDEX(Database!$B$2:$B$60,MATCH($A30,Database!$A$2:$A$60,0))/100,0) | F30: =IFERROR(D30*INDEX(Database!$C$2:$C$60,MATCH($A30,Database!$A$2:$A$60,0))/100,0) | G30: =IFERROR(D30*INDEX(Database!$D$2:$D$60,MATCH($A30,Database!$A$2:$A$60,0))/100,0) | H30: =IFERROR(D30*INDEX(Database!$E$2:$E$60,MATCH($A30,Database!$A$2:$A$60,0))/100,0) | I30: =IFERROR(H30*INDEX(Database!$K$2:$K$60,MATCH($A30,Database!$A$2:$A$60,0)),0) | J30: =IFERROR(D30*INDEX(Database!$F$2:$F$60,MATCH($A30,Database!$A$2:$A$60,0))/100,0) | K30: =IFERROR(D30*INDEX(Database!$G$2:$G$60,MATCH($A30,Database!$A$2:$A$60,0))/100,0) | L30: =IFERROR(D30*INDEX(Database!$H$2:$H$60,MATCH($A30,Database!$A$2:$A$60,0))/100,0) | M30: =IFERROR(D30*INDEX(Database!$I$2:$I$60,MATCH($A30,Database!$A$2:$A$60,0))/100,0) | N30: =IFERROR(D30*INDEX(Database!$J$2:$J$60,MATCH($A30,Database!$A$2:$A$60,0))/100,0)
C31: 1 | D31: =IF(A31="",0,B31*C31) | E31: =IFERROR(D31*INDEX(Database!$B$2:$B$60,MATCH($A31,Database!$A$2:$A$60,0))/100,0) | F31: =IFERROR(D31*INDEX(Database!$C$2:$C$60,MATCH($A31,Database!$A$2:$A$60,0))/100,0) | G31: =IFERROR(D31*INDEX(Database!$D$2:$D$60,MATCH($A31,Database!$A$2:$A$60,0))/100,0) | H31: =IFERROR(D31*INDEX(Database!$E$2:$E$60,MATCH($A31,Database!$A$2:$A$60,0))/100,0) | I31: =IFERROR(H31*INDEX(Database!$K$2:$K$60,MATCH($A31,Database!$A$2:$A$60,0)),0) | J31: =IFERROR(D31*INDEX(Database!$F$2:$F$60,MATCH($A31,Database!$A$2:$A$60,0))/100,0) | K31: =IFERROR(D31*INDEX(Database!$G$2:$G$60,MATCH($A31,Database!$A$2:$A$60,0))/100,0) | L31: =IFERROR(D31*INDEX(Database!$H$2:$H$60,MATCH($A31,Database!$A$2:$A$60,0))/100,0) | M31: =IFERROR(D31*INDEX(Database!$I$2:$I$60,MATCH($A31,Database!$A$2:$A$60,0))/100,0) | N31: =IFERROR(D31*INDEX(Database!$J$2:$J$60,MATCH($A31,Database!$A$2:$A$60,0))/100,0)
C32: 1 | D32: =IF(A32="",0,B32*C32) | E32: =IFERROR(D32*INDEX(Database!$B$2:$B$60,MATCH($A32,Database!$A$2:$A$60,0))/100,0) | F32: =IFERROR(D32*INDEX(Database!$C$2:$C$60,MATCH($A32,Database!$A$2:$A$60,0))/100,0) | G32: =IFERROR(D32*INDEX(Database!$D$2:$D$60,MATCH($A32,Database!$A$2:$A$60,0))/100,0) | H32: =IFERROR(D32*INDEX(Database!$E$2:$E$60,MATCH($A32,Database!$A$2:$A$60,0))/100,0) | I32: =IFERROR(H32*INDEX(Database!$K$2:$K$60,MATCH($A32,Database!$A$2:$A$60,0)),0) | J32: =IFERROR(D32*INDEX(Database!$F$2:$F$60,MATCH($A32,Database!$A$2:$A$60,0))/100,0) | K32: =IFERROR(D32*INDEX(Database!$G$2:$G$60,MATCH($A32,Database!$A$2:$A$60,0))/100,0) | L32: =IFERROR(D32*INDEX(Database!$H$2:$H$60,MATCH($A32,Database!$A$2:$A$60,0))/100,0) | M32: =IFERROR(D32*INDEX(Database!$I$2:$I$60,MATCH($A32,Database!$A$2:$A$60,0))/100,0) | N32: =IFERROR(D32*INDEX(Database!$J$2:$J$60,MATCH($A32,Database!$A$2:$A$60,0))/100,0)
C33: 1 | D33: =IF(A33="",0,B33*C33) | E33: =IFERROR(D33*INDEX(Database!$B$2:$B$60,MATCH($A33,Database!$A$2:$A$60,0))/100,0) | F33: =IFERROR(D33*INDEX(Database!$C$2:$C$60,MATCH($A33,Database!$A$2:$A$60,0))/100,0) | G33: =IFERROR(D33*INDEX(Database!$D$2:$D$60,MATCH($A33,Database!$A$2:$A$60,0))/100,0) | H33: =IFERROR(D33*INDEX(Database!$E$2:$E$60,MATCH($A33,Database!$A$2:$A$60,0))/100,0) | I33: =IFERROR(H33*INDEX(Database!$K$2:$K$60,MATCH($A33,Database!$A$2:$A$60,0)),0) | J33: =IFERROR(D33*INDEX(Database!$F$2:$F$60,MATCH($A33,Database!$A$2:$A$60,0))/100,0) | K33: =IFERROR(D33*INDEX(Database!$G$2:$G$60,MATCH($A33,Database!$A$2:$A$60,0))/100,0) | L33: =IFERROR(D33*INDEX(Database!$H$2:$H$60,MATCH($A33,Database!$A$2:$A$60,0))/100,0) | M33: =IFERROR(D33*INDEX(Database!$I$2:$I$60,MATCH($A33,Database!$A$2:$A$60,0))/100,0) | N33: =IFERROR(D33*INDEX(Database!$J$2:$J$60,MATCH($A33,Database!$A$2:$A$60,0))/100,0)
C34: 1 | D34: =IF(A34="",0,B34*C34) | E34: =IFERROR(D34*INDEX(Database!$B$2:$B$60,MATCH($A34,Database!$A$2:$A$60,0))/100,0) | F34: =IFERROR(D34*INDEX(Database!$C$2:$C$60,MATCH($A34,Database!$A$2:$A$60,0))/100,0) | G34: =IFERROR(D34*INDEX(Database!$D$2:$D$60,MATCH($A34,Database!$A$2:$A$60,0))/100,0) | H34: =IFERROR(D34*INDEX(Database!$E$2:$E$60,MATCH($A34,Database!$A$2:$A$60,0))/100,0) | I34: =IFERROR(H34*INDEX(Database!$K$2:$K$60,MATCH($A34,Database!$A$2:$A$60,0)),0) | J34: =IFERROR(D34*INDEX(Database!$F$2:$F$60,MATCH($A34,Database!$A$2:$A$60,0))/100,0) | K34: =IFERROR(D34*INDEX(Database!$G$2:$G$60,MATCH($A34,Database!$A$2:$A$60,0))/100,0) | L34: =IFERROR(D34*INDEX(Database!$H$2:$H$60,MATCH($A34,Database!$A$2:$A$60,0))/100,0) | M34: =IFERROR(D34*INDEX(Database!$I$2:$I$60,MATCH($A34,Database!$A$2:$A$60,0))/100,0) | N34: =IFERROR(D34*INDEX(Database!$J$2:$J$60,MATCH($A34,Database!$A$2:$A$60,0))/100,0)
A35: TOTAL in batch | B35: =SUM(B10:B34) | D35: =SUM(D10:D34) | E35: =SUM(E10:E34) | F35: =SUM(F10:F34) | G35: =SUM(G10:G34) | H35: =SUM(H10:H34) | I35: =SUM(I10:I34) | J35: =SUM(J10:J34) | K35: =SUM(K10:K34) | ... N35: =SUM(N10:N34)
A36: PER 100 g of finished pickle | E36: =IF($B$5>0,E35/$B$5*100,0) | F36: =IF($B$5>0,F35/$B$5*100,0) | G36: =IF($B$5>0,G35/$B$5*100,0) | H36: =IF($B$5>0,H35/$B$5*100,0) | I36: =IF($B$5>0,I35/$B$5*100,0) | J36: =IF($B$5>0,J35/$B$5*100,0) | K36: =IF($B$5>0,K35/$B$5*100,0) | L36: =IF($B$5>0,L35/$B$5*100,0) | ... N36: =IF($B$5>0,N35/$B$5*100,0)
A38: Sanity checks
A39: Water lost in cooking (g) = weight in minus finished weight | B39: =D35-B5
A40: Yield (finished ÷ in) | B40: =IF(D35>0,B5/D35,0)
A41: Energy per 100 g by Atwater (4×protein + 4×carb + 9×fat), kcal | B41: =4*F36+4*G36+9*J36
A42: Difference vs database energy (should be within ~10%) | B42: =IF(E36>0,B41/E36-1,0)
A43: Salt equivalent per 100 g (g) = sodium × 2.5 ÷ 1000 | B43: =N36*2.5/1000
A44: Warning if finished weight is more than weight in (impossible unless you forgot an ingredient) | B44: =IF(B5>D35,"CHECK: finished weight exceeds inputs","OK")
A46: Why this works: cooking only removes water (and the vinegar's water). Every gram of protein, fat, sugar and sodium you put in stays in the pot, so the batch totals are conserved and per-100 g is simply total ÷ finished weight. The one exception is anything you throw away (drained oil, discarded skins): use the 'fraction' column for that.

Sheet Label
A1: NUTRITIONAL INFORMATION
A2: ="Product: "&Recipe!B4
A3: Approximate values, calculated from ingredient composition (IFCT 2017). Rounded for label use.
A5: Nutrient | B5: Per 100 g | C5: ="Per serve ("&Recipe!B6&" g)" | D5: % RDA per serve*
A6: Energy | B6: =ROUND(Recipe!E36,0)&" kcal" | C6: =ROUND(Recipe!E36*Recipe!$B$6/100,0)&" kcal" | D6: =ROUND(Recipe!E36*Recipe!$B$6/100/2000,2)
A7: Protein | B7: =ROUND(Recipe!F36,1)&" g" | C7: =ROUND(Recipe!F36*Recipe!$B$6/100,1)&" g"
A8: Carbohydrate | B8: =ROUND(Recipe!G36,1)&" g" | C8: =ROUND(Recipe!G36*Recipe!$B$6/100,1)&" g"
A9: of which Total Sugars | B9: =ROUND(Recipe!H36,1)&" g" | C9: =ROUND(Recipe!H36*Recipe!$B$6/100,1)&" g"
A10: of which Added Sugars | B10: =ROUND(Recipe!I36,1)&" g" | C10: =ROUND(Recipe!I36*Recipe!$B$6/100,1)&" g" | D10: =ROUND(Recipe!I36*Recipe!$B$6/100/50,2)
A11: Total Fat | B11: =ROUND(Recipe!J36,1)&" g" | C11: =ROUND(Recipe!J36*Recipe!$B$6/100,1)&" g" | D11: =ROUND(Recipe!J36*Recipe!$B$6/100/67,2)
A12: Saturated Fat | B12: =ROUND(Recipe!K36,1)&" g" | C12: =ROUND(Recipe!K36*Recipe!$B$6/100,1)&" g" | D12: =ROUND(Recipe!K36*Recipe!$B$6/100/22,2)
A13: Trans Fat | B13: =ROUND(Recipe!L36,1)&" g" | C13: =ROUND(Recipe!L36*Recipe!$B$6/100,1)&" g" | D13: =ROUND(Recipe!L36*Recipe!$B$6/100/2,2)
A14: Cholesterol | B14: =ROUND(Recipe!M36,0)&" mg" | C14: =ROUND(Recipe!M36*Recipe!$B$6/100,0)&" mg"
A15: Sodium | B15: =ROUND(Recipe!N36,0)&" mg" | C15: =ROUND(Recipe!N36*Recipe!$B$6/100,0)&" mg" | D15: =ROUND(Recipe!N36*Recipe!$B$6/100/2000,2)
A16: *% RDA based on a 2000 kcal diet (FSSAI reference values: added sugar 50 g, total fat 67 g, saturated fat 22 g, trans fat 2 g, sodium 2000 mg). Optional on the label; mandatory only if you make a nutrition claim.
A18: QUID: % of named ingredients (ingoing weight ÷ finished weight)
A19: Ingredient | B19: % on label
A20: Prawns, fresh, cleaned | B20: =IFERROR(SUMIFS(Recipe!$B$10:$B$34,Recipe!$A$10:$A$34,A20)/Recipe!$B$5,0)
A21: Dates, dried | B21: =IFERROR(SUMIFS(Recipe!$B$10:$B$34,Recipe!$A$10:$A$34,A21)/Recipe!$B$5,0)
A23: Note: FSSAI QUID uses the weight of the ingredient at the time it was added, divided by the total finished product. For prawns that fry down, this can exceed the fried weight share; that is expected and allowed. Change the ingredient name in the yellow cell to match the Recipe sheet exactly.
A25: Ingredient list order (descending by ingoing weight, FSSAI requirement)
A26: Rank | B26: Ingredient | C26: Weight in (g) | D26: % of finished
A27: 1 | B27: =IFERROR(INDEX(Recipe!$A$10:$A$34,MATCH(C27,Recipe!$B$10:$B$34,0)+COUNTIF(C$27:C27,C27)-1),"") | C27: =IFERROR(LARGE(Recipe!$B$10:$B$34,1),"") | D27: =IFERROR(C27/Recipe!$B$5,"")
A28: 2 | B28: =IFERROR(INDEX(Recipe!$A$10:$A$34,MATCH(C28,Recipe!$B$10:$B$34,0)+COUNTIF(C$27:C28,C28)-1),"") | C28: =IFERROR(LARGE(Recipe!$B$10:$B$34,2),"") | D28: =IFERROR(C28/Recipe!$B$5,"")
A29: 3 | B29: =IFERROR(INDEX(Recipe!$A$10:$A$34,MATCH(C29,Recipe!$B$10:$B$34,0)+COUNTIF(C$27:C29,C29)-1),"") | C29: =IFERROR(LARGE(Recipe!$B$10:$B$34,3),"") | D29: =IFERROR(C29/Recipe!$B$5,"")
A30: 4 | B30: =IFERROR(INDEX(Recipe!$A$10:$A$34,MATCH(C30,Recipe!$B$10:$B$34,0)+COUNTIF(C$27:C30,C30)-1),"") | C30: =IFERROR(LARGE(Recipe!$B$10:$B$34,4),"") | D30: =IFERROR(C30/Recipe!$B$5,"")
A31: 5 | B31: =IFERROR(INDEX(Recipe!$A$10:$A$34,MATCH(C31,Recipe!$B$10:$B$34,0)+COUNTIF(C$27:C31,C31)-1),"") | C31: =IFERROR(LARGE(Recipe!$B$10:$B$34,5),"") | D31: =IFERROR(C31/Recipe!$B$5,"")
A32: 6 | B32: =IFERROR(INDEX(Recipe!$A$10:$A$34,MATCH(C32,Recipe!$B$10:$B$34,0)+COUNTIF(C$27:C32,C32)-1),"") | C32: =IFERROR(LARGE(Recipe!$B$10:$B$34,6),"") | D32: =IFERROR(C32/Recipe!$B$5,"")
A33: 7 | B33: =IFERROR(INDEX(Recipe!$A$10:$A$34,MATCH(C33,Recipe!$B$10:$B$34,0)+COUNTIF(C$27:C33,C33)-1),"") | C33: =IFERROR(LARGE(Recipe!$B$10:$B$34,7),"") | D33: =IFERROR(C33/Recipe!$B$5,"")
A34: 8 | B34: =IFERROR(INDEX(Recipe!$A$10:$A$34,MATCH(C34,Recipe!$B$10:$B$34,0)+COUNTIF(C$27:C34,C34)-1),"") | C34: =IFERROR(LARGE(Recipe!$B$10:$B$34,8),"") | D34: =IFERROR(C34/Recipe!$B$5,"")
A35: 9 | B35: =IFERROR(INDEX(Recipe!$A$10:$A$34,MATCH(C35,Recipe!$B$10:$B$34,0)+COUNTIF(C$27:C35,C35)-1),"") | C35: =IFERROR(LARGE(Recipe!$B$10:$B$34,9),"") | D35: =IFERROR(C35/Recipe!$B$5,"")
A36: 10 | B36: =IFERROR(INDEX(Recipe!$A$10:$A$34,MATCH(C36,Recipe!$B$10:$B$34,0)+COUNTIF(C$27:C36,C36)-1),"") | C36: =IFERROR(LARGE(Recipe!$B$10:$B$34,10),"") | D36: =IFERROR(C36/Recipe!$B$5,"")
A37: 11 | B37: =IFERROR(INDEX(Recipe!$A$10:$A$34,MATCH(C37,Recipe!$B$10:$B$34,0)+COUNTIF(C$27:C37,C37)-1),"") | C37: =IFERROR(LARGE(Recipe!$B$10:$B$34,11),"") | D37: =IFERROR(C37/Recipe!$B$5,"")
A38: 12 | B38: =IFERROR(INDEX(Recipe!$A$10:$A$34,MATCH(C38,Recipe!$B$10:$B$34,0)+COUNTIF(C$27:C38,C38)-1),"") | C38: =IFERROR(LARGE(Recipe!$B$10:$B$34,12),"") | D38: =IFERROR(C38/Recipe!$B$5,"")
A39: 13 | B39: =IFERROR(INDEX(Recipe!$A$10:$A$34,MATCH(C39,Recipe!$B$10:$B$34,0)+COUNTIF(C$27:C39,C39)-1),"") | C39: =IFERROR(LARGE(Recipe!$B$10:$B$34,13),"") | D39: =IFERROR(C39/Recipe!$B$5,"")
A40: 14 | B40: =IFERROR(INDEX(Recipe!$A$10:$A$34,MATCH(C40,Recipe!$B$10:$B$34,0)+COUNTIF(C$27:C40,C40)-1),"") | C40: =IFERROR(LARGE(Recipe!$B$10:$B$34,14),"") | D40: =IFERROR(C40/Recipe!$B$5,"")
A41: 15 | B41: =IFERROR(INDEX(Recipe!$A$10:$A$34,MATCH(C41,Recipe!$B$10:$B$34,0)+COUNTIF(C$27:C41,C41)-1),"") | C41: =IFERROR(LARGE(Recipe!$B$10:$B$34,15),"") | D41: =IFERROR(C41/Recipe!$B$5,"")
A43: Caution: ingredients with identical weights (e.g. the two chilli powders at 60 g) are listed in sheet order. Vinegar ranks high by ingoing weight but FSSAI lets you list it by what remains after cooking; your costing doc already does that. The ranking here is a starting point, not the final print order.

Sheet Costing
A1: Batch costing (weights linked from the Recipe sheet)
A2: Yellow cells: your prices, in ₹ per kg of the ingredient as bought. Weights come from Recipe automatically.
A4: Ingredient | B4: Weight in (g) | C4: Price (₹ per kg) | D4: Cost (₹) | E4: % of batch cost | F4: Price note
A5: =Recipe!A10 | B5: =Recipe!B10 | C5: 370 | D5: =B5*C5/1000 | E5: =IF($D$22>0,D5/$D$22,0) | F5: NOT GIVEN. From costing doc: ₹1,000 for 2.7 kg. Confirm.
A6: =Recipe!A11 | B6: =Recipe!B11 | C6: 145 | D6: =B6*C6/1000 | E6: =IF($D$22>0,D6/$D$22,0) | F6: Stated
A7: =Recipe!A12 | B7: =Recipe!B12 | C7: 250 | D7: =B7*C7/1000 | E7: =IF($D$22>0,D7/$D$22,0) | F7: Gingelly (sesame) oil. ₹230 per litre ÷ 0.92 kg per litre = ₹250 per kg. Confirmed 2026-09-04.
A8: =Recipe!A13 | B8: =Recipe!B13 | C8: 11 | D8: =B8*C8/1000 | E8: =IF($D$22>0,D8/$D$22,0) | F8: ₹11 per litre; 1 L ≈ 1 kg
A9: =Recipe!A14 | B9: =Recipe!B14 | C9: 200 | D9: =B9*C9/1000 | E9: =IF($D$22>0,D9/$D$22,0) | F9: Stated
A10: =Recipe!A15 | B10: =Recipe!B15 | C10: 50 | D10: =B10*C10/1000 | E10: =IF($D$22>0,D10/$D$22,0) | F10: Stated
A11: =Recipe!A16 | B11: =Recipe!B16 | C11: 150 | D11: =B11*C11/1000 | E11: =IF($D$22>0,D11/$D$22,0) | F11: Stated
A12: =Recipe!A17 | B12: =Recipe!B17 | C12: 860 | D12: =B12*C12/1000 | E12: =IF($D$22>0,D12/$D$22,0) | F12: Stated
A13: =Recipe!A18 | B13: =Recipe!B18 | C13: 440 | D13: =B13*C13/1000 | E13: =IF($D$22>0,D13/$D$22,0) | F13: Stated
A14: =Recipe!A19 | B14: =Recipe!B19 | C14: 70 | D14: =B14*C14/1000 | E14: =IF($D$22>0,D14/$D$22,0) | F14: Stated
A15: =Recipe!A20 | B15: =Recipe!B20 | C15: 1350 | D15: =B15*C15/1000 | E15: =IF($D$22>0,D15/$D$22,0) | F15: ₹27 for 20 g = ₹1,350 per kg
A16: =Recipe!A21 | B16: =Recipe!B21 | C16: 120 | D16: =B16*C16/1000 | E16: =IF($D$22>0,D16/$D$22,0) | F16: NOT GIVEN. Placeholder. Confirm.
... A21: =Recipe!A26 | B21: =Recipe!B26 | C21: 320 | D21: =B21*C21/1000 | E21: =IF($D$22>0,D21/$D$22,0) | F21: Stated; quantity not yet given
A22: TOTAL ingredients per batch | B22: =SUM(B5:B21) | D22: =SUM(D5:D21)
A24: Per jar
A25: Finished batch weight (g), from Recipe | B25: =Recipe!B5
A26: Jar size (g) | B26: 200
A27: Jars per batch | B27: =B25/B26 | C27: Shipping box is per order, not per jar; add separately
A28: Ingredient cost per jar (₹) | B28: =D22/B27
A29: Ingredient cost per kg (₹) | B29: =D22/B25*1000
A30: Gas, labour, wastage per jar (₹) | B30: 40 | C30: From your costing doc; adjust
A31: Jar, lid, label, note per jar (₹) | B31: 40 | C31: From your costing doc; adjust
A32: All-in cost per jar (₹) | B32: =B28+B30+B31
A33: Sell price per jar (₹) | B33: 499
A34: Profit per jar (₹) | B34: =B33-B32
A35: Margin | B35: =IF(B33>0,B34/B33,0)
A36: Profit per batch (₹) | B36: =B34*B27
